LICENSE
MANIFEST.in
history.md
readme.md
setup.py
examples/demo.fasta
examples/demo.fastq
examples/demo.m8
examples/demo.sam
humann2/__init__.py
humann2/check.py
humann2/config.py
humann2/humann2.cfg
humann2/humann2.py
humann2/store.py
humann2/utilities.py
humann2.egg-info/PKG-INFO
humann2.egg-info/SOURCES.txt
humann2.egg-info/dependency_links.txt
humann2.egg-info/entry_points.txt
humann2.egg-info/not-zip-safe
humann2.egg-info/top_level.txt
humann2/data/chocophlan_DEMO/g__Bacteroides.s__Bacteroides_dorei.centroids.v0.1.1.ffn.gz
humann2/data/chocophlan_DEMO/g__Bacteroides.s__Bacteroides_vulgatus.centroids.v0.1.1.ffn.gz
humann2/data/misc/KeggOrgId2OrgNameTable.txt
humann2/data/misc/README.txt
humann2/data/misc/map_eggnog_name.txt.gz
humann2/data/misc/map_go_name.txt.gz
humann2/data/misc/map_kegg-mdl_name.txt.gz
humann2/data/misc/map_kegg-pwy_name.txt.gz
humann2/data/misc/map_ko_name.txt.gz
humann2/data/misc/map_level4ec_name.txt.gz
humann2/data/misc/map_metacyc-pwy_name.txt.gz
humann2/data/misc/map_metacyc-rxn_name.txt.gz
humann2/data/misc/map_pfam_name.txt.gz
humann2/data/misc/map_transporter_uniref50.txt.gz
humann2/data/misc/map_uniref50_name.txt.bz2
humann2/data/pathways/metacyc_pathways
humann2/data/pathways/metacyc_pathways_structured
humann2/data/pathways/metacyc_pathways_structured_filtered
humann2/data/pathways/metacyc_pathways_to_organisms
humann2/data/pathways/metacyc_reactions_level4ec_only.uniref.bz2
humann2/data/pathways/unipathway_pathways
humann2/data/pathways/unipathway_uniprots.uniref.bz2
humann2/data/uniref_DEMO/uniref90_demo_prots.dmnd
humann2/data/uniref_DEMO/uniref90_demo_prots.faa
humann2/quantify/MinPath12hmp.py
humann2/quantify/__init__.py
humann2/quantify/chi2cdf.py
humann2/quantify/families.py
humann2/quantify/modules.py
humann2/quantify/xipe.py
humann2/search/__init__.py
humann2/search/blastx_coverage.py
humann2/search/nucleotide.py
humann2/search/pick_frames.py
humann2/search/prescreen.py
humann2/search/translated.py
humann2/tests/__init__.py
humann2/tests/advanced_tests_blastx_coverage.py
humann2/tests/advanced_tests_nucleotide_search.py
humann2/tests/advanced_tests_quantify_families.py
